notesdir/__init__.py
notesdir/__main__.py
notesdir/api.py
notesdir/cli.py
notesdir/conf.py
notesdir/models.py
notesdir/rearrange.py
notesdir/accessors/__init__.py
notesdir/accessors/base.py
notesdir/accessors/delegating.py
notesdir/accessors/html.py
notesdir/accessors/markdown.py
notesdir/accessors/pdf.py
notesdir/repos/__init__.py
notesdir/repos/base.py
notesdir/repos/direct.py
notesdir/repos/sqlite.py
notesdir-0.0.5.dist-info/LICENSE
notesdir-0.0.5.dist-info/METADATA
notesdir-0.0.5.dist-info/WHEEL
notesdir-0.0.5.dist-info/entry_points.txt
notesdir-0.0.5.dist-info/top_level.txt
notesdir-0.0.5.dist-info/RECORD
